storage/__init__.py
storage/common/__init__.py
storage/common/data_page.py
storage/common/utils/__init__.py
storage/common/utils/storage_utils.py
storage/mongo/__init__.py
storage/mongo/mongo_template.py
storage/mysql/__init__.py
storage/mysql/mysql_template.py
storage/oracle/__init__.py
storage/oracle/oracle_template.py
storage/storage/__init__.py
storage/storage/engine_adaptor.py
storage/storage/exception/__init__.py
storage/storage/exception/exception.py
storage/storage/storage_interface.py
storage/storage/storage_template.py
storage/storage/utils/__init__.py
storage/storage/utils/table_utils.py
watchmen_storage_engine-15.2.1.dist-info/LICENSE
watchmen_storage_engine-15.2.1.dist-info/WHEEL
watchmen_storage_engine-15.2.1.dist-info/METADATA
watchmen_storage_engine-15.2.1.dist-info/RECORD
