Metadata-Version: 2.1
Name: watchmen-storage-engine
Version: 15.2.1
Summary: 
Author: luke0623
Author-email: luke0623@outlook.com
Requires-Python: >=3.9,<4.0
Classifier: Programming Language :: Python :: 3
Classifier: Programming Language :: Python :: 3.10
Classifier: Programming Language :: Python :: 3.9
Requires-Dist: SQLAlchemy (>=1.4.27,<2.0.0)
Requires-Dist: arrow (>=1.1.0,<2.0.0)
Requires-Dist: pydantic (>=1.8.2,<2.0.0)
